UcsdCogs108ShujuKexueShizhanZhongwenBiji/README.md
UcsdCogs108ShujuKexueShizhanZhongwenBiji/__init__.py
UcsdCogs108ShujuKexueShizhanZhongwenBiji/__main__.py
UcsdCogs108ShujuKexueShizhanZhongwenBiji/file.epub
UcsdCogs108ShujuKexueShizhanZhongwenBiji/index.html
UcsdCogs108ShujuKexueShizhanZhongwenBiji/css/__init__.py
UcsdCogs108ShujuKexueShizhanZhongwenBiji/css/annotations.css
UcsdCogs108ShujuKexueShizhanZhongwenBiji/css/main.css
UcsdCogs108ShujuKexueShizhanZhongwenBiji/css/normalize.css
UcsdCogs108ShujuKexueShizhanZhongwenBiji/css/popup.css
UcsdCogs108ShujuKexueShizhanZhongwenBiji/font/__init__.py
UcsdCogs108ShujuKexueShizhanZhongwenBiji/font/fontello.eot
UcsdCogs108ShujuKexueShizhanZhongwenBiji/font/fontello.svg
UcsdCogs108ShujuKexueShizhanZhongwenBiji/font/fontello.ttf
UcsdCogs108ShujuKexueShizhanZhongwenBiji/font/fontello.woff
UcsdCogs108ShujuKexueShizhanZhongwenBiji/img/__init__.py
UcsdCogs108ShujuKexueShizhanZhongwenBiji/img/annotator-glyph-sprite.png
UcsdCogs108ShujuKexueShizhanZhongwenBiji/img/annotator-icon-sprite.png
UcsdCogs108ShujuKexueShizhanZhongwenBiji/img/apple-touch-icon.png
UcsdCogs108ShujuKexueShizhanZhongwenBiji/img/cancelfullscreen.png
UcsdCogs108ShujuKexueShizhanZhongwenBiji/img/close.png
UcsdCogs108ShujuKexueShizhanZhongwenBiji/img/fullscreen.png
UcsdCogs108ShujuKexueShizhanZhongwenBiji/img/loader.gif
UcsdCogs108ShujuKexueShizhanZhongwenBiji/img/menu-icon.png
UcsdCogs108ShujuKexueShizhanZhongwenBiji/img/save.png
UcsdCogs108ShujuKexueShizhanZhongwenBiji/img/saved.png
UcsdCogs108ShujuKexueShizhanZhongwenBiji/img/settings-s.png
UcsdCogs108ShujuKexueShizhanZhongwenBiji/img/settings.png
UcsdCogs108ShujuKexueShizhanZhongwenBiji/img/star.png
UcsdCogs108ShujuKexueShizhanZhongwenBiji/js/__init__.py
UcsdCogs108ShujuKexueShizhanZhongwenBiji/js/epub.js
UcsdCogs108ShujuKexueShizhanZhongwenBiji/js/epub.min.js
UcsdCogs108ShujuKexueShizhanZhongwenBiji/js/epub.min.map
UcsdCogs108ShujuKexueShizhanZhongwenBiji/js/hooks.min.js
ucsd_cogs108_shuju_kexue_shizhan_zhongwen_biji-2024.3.5.0.dist-info/METADATA
ucsd_cogs108_shuju_kexue_shizhan_zhongwen_biji-2024.3.5.0.dist-info/WHEEL
ucsd_cogs108_shuju_kexue_shizhan_zhongwen_biji-2024.3.5.0.dist-info/entry_points.txt
ucsd_cogs108_shuju_kexue_shizhan_zhongwen_biji-2024.3.5.0.dist-info/top_level.txt
ucsd_cogs108_shuju_kexue_shizhan_zhongwen_biji-2024.3.5.0.dist-info/RECORD
